MANIFEST.in
README.md
distribute_setup.py
setup.py
carrie/__init__.py
carrie/daemon.py
carrie/fifo.py
carrie/log.py
carrie/server.py
carrie/xorg.py
carrie/xscreensaver.py
carrie.egg-info/PKG-INFO
carrie.egg-info/SOURCES.txt
carrie.egg-info/dependency_links.txt
carrie.egg-info/entry_points.txt
carrie.egg-info/requires.txt
carrie.egg-info/top_level.txt
carrie/static/carrie.css
carrie/static/index.js
carrie/static/jquery-1.7.min.js
carrie/static/jquery-ui/css/smoothness/jquery-ui-1.8.16.custom.css
carrie/static/jquery-ui/css/smoothness/images/ui-bg_flat_0_aaaaaa_40x100.png
carrie/static/jquery-ui/css/smoothness/images/ui-bg_flat_75_ffffff_40x100.png
carrie/static/jquery-ui/css/smoothness/images/ui-bg_glass_55_fbf9ee_1x400.png
carrie/static/jquery-ui/css/smoothness/images/ui-bg_glass_65_ffffff_1x400.png
carrie/static/jquery-ui/css/smoothness/images/ui-bg_glass_75_dadada_1x400.png
carrie/static/jquery-ui/css/smoothness/images/ui-bg_glass_75_e6e6e6_1x400.png
carrie/static/jquery-ui/css/smoothness/images/ui-bg_glass_95_fef1ec_1x400.png
carrie/static/jquery-ui/css/smoothness/images/ui-bg_highlight-soft_75_cccccc_1x100.png
carrie/static/jquery-ui/css/smoothness/images/ui-icons_222222_256x240.png
carrie/static/jquery-ui/css/smoothness/images/ui-icons_2e83ff_256x240.png
carrie/static/jquery-ui/css/smoothness/images/ui-icons_454545_256x240.png
carrie/static/jquery-ui/css/smoothness/images/ui-icons_888888_256x240.png
carrie/static/jquery-ui/css/smoothness/images/ui-icons_cd0a0a_256x240.png
carrie/static/jquery-ui/js/jquery-ui-1.8.16.custom.min.js
carrie/templates/about.html
carrie/templates/index.html