Metadata-Version: 1.0
Name: carrie
Version: 0.3
Summary: Remote control of media players via web or Android phone
Home-page: http://github.com/mjem/carrie
Author: Mike Elson
Author-email: mike.elson@gmail.com
License: GPL
Keywords: mplayer youtube iplayer android
Platform: UNKNOWN
Classifier: Framework :: Django
Classifier: Topic :: Software Development
Classifier: License :: OSI Approved :: GNU General Public License (GPL)
Classifier: Intended Audience :: End Users/Desktop
Classifier: Operating System :: POSIX :: Linux
Classifier: Programming Language :: Python :: 2.7
Classifier: Topic :: Internet :: WWW/HTTP
Classifier: Topic :: Multimedia :: Sound/Audio
